click_groups/__init__.py
click_groups/_version.py
click_groups/core.py
click_groups/py.typed
click_groups-0.1.6.dist-info/licenses/LICENSE
click_groups-0.1.6.dist-info/METADATA
click_groups-0.1.6.dist-info/WHEEL
click_groups-0.1.6.dist-info/top_level.txt
click_groups-0.1.6.dist-info/RECORD
